swheel/__main__.py
swheel-0.1.3.dist-info/LICENSE.txt
swheel-0.1.3.dist-info/METADATA
swheel-0.1.3.dist-info/WHEEL
swheel-0.1.3.dist-info/RECORD
